MANIFEST.in
README.rst
setup.py
auth_remember/__init__.py
auth_remember/admin.py
auth_remember/auth_utils.py
auth_remember/backend.py
auth_remember/middleware.py
auth_remember/models.py
auth_remember/settings.py
auth_remember/tests.py
auth_remember/utils.py
auth_remember/management/__init__.py
auth_remember/management/commands/__init__.py
auth_remember/management/commands/cleanup_remember_tokens.py
auth_remember/migrations/0001_initial.py
auth_remember/migrations/__init__.py
django_auth_remember.egg-info/PKG-INFO
django_auth_remember.egg-info/SOURCES.txt
django_auth_remember.egg-info/dependency_links.txt
django_auth_remember.egg-info/not-zip-safe
django_auth_remember.egg-info/requires.txt
django_auth_remember.egg-info/top_level.txt