Metadata-Version: 1.0
Name: django-auth-remember
Version: 0.3
Summary: Django app for remember-me functionality (using a token)
Home-page: https://github.com/ailabs/django-auth-remember/
Author: Michael van Tellingen
Author-email: m.vantellingen@auto-interactive.nl
License: MIT
Platform: UNKNOWN
Classifier: Development Status :: 4 - Beta
Classifier: Environment :: Web Environment
Classifier: Framework :: Django
Classifier: Intended Audience :: Developers
Classifier: License :: OSI Approved :: MIT License
Classifier: Operating System :: OS Independent
Classifier: Programming Language :: Python
Classifier: Topic :: Software Development
